examples/__init__.py
examples/delete_all_managed_profiles.py
examples/fetch_all_managed_profiles.py
examples/intro.py
examples/update_profiles.py
geni/__init__.py
geni/geni.py
geni/profile.py
geni/stats.py
geni/user.py
geni/version.py
geni/internal/__init__.py
geni/internal/auth.py
geni/internal/caller.py
geni/internal/ratelimiter.py
tests/__init__.py
tests/test_geni.py
tests/test_profile.py
tests/test_stats.py
tests/test_user.py
tests/internal/__init__.py
tests/internal/helper.py
tests/internal/test_auth.py
tests/internal/test_caller.py
tests/internal/test_ratelimiter.py
tests/internal/fixtures/__init__.py
tests/internal/fixtures/profile.py
tests/internal/fixtures/response.py
geniapi-0.1.0.dist-info/LICENSE
geniapi-0.1.0.dist-info/METADATA
geniapi-0.1.0.dist-info/WHEEL
geniapi-0.1.0.dist-info/top_level.txt
geniapi-0.1.0.dist-info/RECORD
