Metadata-Version: 2.2
Name: geniapi
Version: 0.1.0
Summary: Python client library for the Geni.com public REST API
Author: Dmitry Bryndin
License: Copyright 2025 Dmitry Bryndin
Project-URL: Homepage, https://github.com/bryndin/geni
Keywords: geni,api,client,geni.com
Classifier: Development Status :: 4 - Beta
Classifier: Programming Language :: Python :: 3.10
Classifier: License :: OSI Approved :: MIT License
Classifier: Operating System :: OS Independent
Classifier: Intended Audience :: Developers
Requires-Python: >=3.10
License-File: LICENSE
Requires-Dist: requests>=2.32.3
Provides-Extra: dev
Requires-Dist: pytest>=8.3.4; extra == "dev"
Requires-Dist: types-requests>=2.32.0.20241016; extra == "dev"
